mitoolspro/__init__.py
mitoolspro/cli.py
mitoolspro/clustering/__init__.py
mitoolspro/clustering/clustering_algorithms.py
mitoolspro/clustering/clustering_evaluations.py
mitoolspro/clustering/clustering_visualizations.py
mitoolspro/databases/__init__.py
mitoolspro/databases/sql_alchemy.py
mitoolspro/databases/sql_lite.py
mitoolspro/document/__init__.py
mitoolspro/document/document_structure.py
mitoolspro/document/from_docx.py
mitoolspro/document/from_pdf.py
mitoolspro/document/runs_utils.py
mitoolspro/document/utils.py
mitoolspro/document/write_document.py
mitoolspro/document/fonts/__init__.py
mitoolspro/document/fonts/fonts.py
mitoolspro/economic_complexity/__init__.py
mitoolspro/economic_complexity/economic_complexity.py
mitoolspro/economic_complexity/objects.py
mitoolspro/economic_complexity/plots.py
mitoolspro/economic_complexity/country_utils/__init__.py
mitoolspro/economic_complexity/country_utils/rename.py
mitoolspro/economic_complexity/country_utils/country_converter/__init__.py
mitoolspro/economic_complexity/country_utils/country_converter/country_converter.py
mitoolspro/economic_complexity/country_utils/country_converter/version.py
mitoolspro/exceptions/__init__.py
mitoolspro/exceptions/custom_exceptions.py
mitoolspro/files/__init__.py
mitoolspro/files/doc_handlers.py
mitoolspro/files/excel_handlers.py
mitoolspro/files/file_conversion.py
mitoolspro/files/file_functions.py
mitoolspro/files/ics_handlers.py
mitoolspro/files/pdf_handlers.py
mitoolspro/files/read_write.py
mitoolspro/google_utils/__init__.py
mitoolspro/google_utils/places/__init__.py
mitoolspro/google_utils/places/client.py
mitoolspro/google_utils/places/models.py
mitoolspro/google_utils/places/plots.py
mitoolspro/google_utils/places/process.py
mitoolspro/google_utils/places/saturation.py
mitoolspro/google_utils/places/search.py
mitoolspro/google_utils/places/utils.py
mitoolspro/google_utils/places/workflow.py
mitoolspro/google_utils/youtube/__init__.py
mitoolspro-1.0.1.dist-info/METADATA
mitoolspro-1.0.1.dist-info/WHEEL
mitoolspro-1.0.1.dist-info/entry_points.txt
mitoolspro-1.0.1.dist-info/licenses/LICENSE
mitoolspro-1.0.1.dist-info/RECORD
